{
  "creds": {
    "noiseKey": {
      "private": {
        "type": "Buffer",
        "data": "OL0OpSpgmc/oyXpQ/IPHZPB8F1X/TIjaHnXnVHoNA0M="
      },
      "public": {
        "type": "Buffer",
        "data": "v0vWwYTc9Gg7eDQiLh/Zp1C9mhXsysmitdxB4hj9WX4="
      }
    },
    "signedIdentityKey": {
      "private": {
        "type": "Buffer",
        "data": "GFmywD0mfaZ8A3x+Rm8tXFv8c2OUYuWTm5L5zrOb3kg="
      },
      "public": {
        "type": "Buffer",
        "data": "AVZhejVHgP2LHO8jexP0JxT+SZ8+Ub+H2jPk5h8gWBU="
      }
    },
    "signedPreKey": {
      "keyPair": {
        "private": {
          "type": "Buffer",
          "data": "sPQA2w6hvpQ3Ty5fka3LQDO6pCC9ukC7FaeU616rIV4="
        },
        "public": {
          "type": "Buffer",
          "data": "Q/QalF0K2QRu2HF5kiDvnjNXs8JZugj4t7jj6WfTAR8="
        }
      },
      "signature": {
        "type": "Buffer",
        "data": "rLGbC0wbf0YXIDrke1iHWdvHrmy3Fz3ZRY7aveGNUzkHFtgt6+944jclII9qWCbvOo2jsrFTRu3O2R4OM6p6iw=="
      },
      "keyId": 1
    },
    "registrationId": 70,
    "advSecretKey": "PoG/cV7ZYLnAV6H4d/8rnoJyLqWT27L9fVv0ki6tLt4=",
    "processedHistoryMessages": [
      {
        "key": {
          "remoteJid": "6285947674337@s.whatsapp.net",
          "fromMe": true,
          "id": "039E425CDF2222798A69E694B5FBAE55"
        },
        "messageTimestamp": 1668082605
      },
      {
        "key": {
          "remoteJid": "6285947674337@s.whatsapp.net",
          "fromMe": true,
          "id": "0C793B4C920A272FEAD2C24B40906185"
        },
        "messageTimestamp": 1668082605
      },
      {
        "key": {
          "remoteJid": "6285947674337@s.whatsapp.net",
          "fromMe": true,
          "id": "4EA9CE97D394544B55B59C2CD9B41355"
        },
        "messageTimestamp": 1668082628
      }
    ],
    "nextPreKeyId": 31,
    "firstUnuploadedPreKeyId": 31,
    "accountSettings": {
      "unarchiveChats": false
    },
    "account": {
      "details": "CIXixuoEEKfXs5sGGAE=",
      "accountSignatureKey": "tGt8kdapobdC4lCxBIK9OpmAgao5qKSGO62jguBnXTI=",
      "accountSignature": "9V1zrVjfgTzCGMV+g00oh45iVUaM/sYz22iyjsuqsVwX1iBkR+pzF3lsbuAE5o9cKEr7R/Xs4xy8aM73WVFjAg==",
      "deviceSignature": "/Qn6PH8fg+3cRkzMs6Sp/BhYrOj2GZeoJu/PFTU/NvsfG0rrV+Mxt6kdi9vHRrWnBuY7d7+QhVXWj6atkw9uiA=="
    },
    "me": {
      "id": "6285947674337:8@s.whatsapp.net",
      "name": "dapin"
    },
    "signalIdentities": [
      {
        "identifier": {
          "name": "6285947674337:8@s.whatsapp.net",
          "deviceId": 0
        },
        "identifierKey": {
          "type": "Buffer",
          "data": "BbRrfJHWqaG3QuJQsQSCvTqZgIGqOaikhjuto4LgZ10y"
        }
      }
    ],
    "platform": "android",
    "lastAccountSyncTimestamp": 1668082602,
    "myAppStateKeyId": "AAAAAPTh"
  },
  "keys": {
    "preKeys": {
      "1": null,
      "2": {
        "private": {
          "type": "Buffer",
          "data": "gM2gVe1G3AHNGBVRgL8aHO8OJw3pDMhEZse8LlmJKVY="
        },
        "public": {
          "type": "Buffer",
          "data": "9uABUeVRcClbGOgTLAAsUa1Kq0b1sYM9888gAi2Sfl0="
        }
      },
      "3": null,
      "4": {
        "private": {
          "type": "Buffer",
          "data": "cIs/Tfk/Sos44L/PXD64gER1o8u1JJO0WxKACYvCBHU="
        },
        "public": {
          "type": "Buffer",
          "data": "f8r7NQ5Ek6PP4EVlN5JqHzk92mO95/0b+JxelMXTrWs="
        }
      },
      "5": {
        "private": {
          "type": "Buffer",
          "data": "gPfubc6njGXJcKX8Sl0lP+jdR0Y+XReOXsu3RxiuGXE="
        },
        "public": {
          "type": "Buffer",
          "data": "AsGc5ZOb10o6r4BIC0937CCfrKdoE6gD7+6PRmwy3RE="
        }
      },
      "6": {
        "private": {
          "type": "Buffer",
          "data": "0D5HTMfS4s/8hSCr/mto/jBKpseMylYPsBks0Z+B6EU="
        },
        "public": {
          "type": "Buffer",
          "data": "Pz6AlMGo0rIPM/1a3mvDotg4FUYrsCTJzAsqSVDOP0E="
        }
      },
      "7": {
        "private": {
          "type": "Buffer",
          "data": "qMZ+UrBrwwkFHnEpOq5/7vBtJCmdViGqo7ygbf6kwFo="
        },
        "public": {
          "type": "Buffer",
          "data": "jRgSHRZgNF4d7yEhFStFQkPgLfv5BX18YLTUZjT7eWc="
        }
      },
      "8": {
        "private": {
          "type": "Buffer",
          "data": "wIWZ8wnIllNHHfxGUrJS4Fi5cwitrW6dcKQHhoVSrl8="
        },
        "public": {
          "type": "Buffer",
          "data": "YoeHo77SPDasykM/IaUEsgiyLg9cvy20r59b1NA2zE8="
        }
      },
      "9": {
        "private": {
          "type": "Buffer",
          "data": "eGsLauatd0V619HELGEC5gn66a688Kj/0v9u7qHENmw="
        },
        "public": {
          "type": "Buffer",
          "data": "9qgtbVop4tWhGgcFuzbDwALlBXJGArx/J938HpXqGVU="
        }
      },
      "10": {
        "private": {
          "type": "Buffer",
          "data": "sPwXjpZUN4Nnm30hz2pdT0Vf6CR4jY3dyrfAMUktu1s="
        },
        "public": {
          "type": "Buffer",
          "data": "7yFS4pccVrbOsxtbv66hzcSOWAHTkie1mhQ6ySj1BhQ="
        }
      },
      "11": {
        "private": {
          "type": "Buffer",
          "data": "WHRmKjQET3A7laFqt0RpRw5VR6gbIN5AbmHJM8ui+3E="
        },
        "public": {
          "type": "Buffer",
          "data": "YEefLf2yPvUQXSpXk6G6ArWvGPvtCqtDtCpZoXeHxQM="
        }
      },
      "12": {
        "private": {
          "type": "Buffer",
          "data": "UMQfK5761UabsEnnDp3WEa+O69Cg3kmqJOiBPdF4Xl0="
        },
        "public": {
          "type": "Buffer",
          "data": "CCbcMk+tBr15ju6mYDgxJXptJKFEbis/2B3b2Rkdl30="
        }
      },
      "13": {
        "private": {
          "type": "Buffer",
          "data": "MExA4NJdgHCYRPgQwUiOvLEL6leJK8d+02nVyNerP0Y="
        },
        "public": {
          "type": "Buffer",
          "data": "nePMkLrf8CCD6nSGhyjTFhe6N5JuhDgbmsJcf9ib1wc="
        }
      },
      "14": {
        "private": {
          "type": "Buffer",
          "data": "YLd6h6A9lqE2nfp1Ba70lH1+tJM8LlpSbbK3TrXT2HY="
        },
        "public": {
          "type": "Buffer",
          "data": "PJoy0P9mvWltY9e+3+HgZJHrz+XU3WU24zywPkqPyyk="
        }
      },
      "15": {
        "private": {
          "type": "Buffer",
          "data": "OOJuNFKmcIBShQ+zt0qsGoIB50MqbSs/Hx7q2gwYL1c="
        },
        "public": {
          "type": "Buffer",
          "data": "2eH15nSudVS9UNqbLeyFwmqy81jOYOy3qL8JRx0so1w="
        }
      },
      "16": null,
      "17": null,
      "18": {
        "private": {
          "type": "Buffer",
          "data": "SIFHmN0LuNuiQMZ2raQe14t6HJilc4Hf6unpxE9czlU="
        },
        "public": {
          "type": "Buffer",
          "data": "7OdJ0Gv6xcPu5VW0j2tIbT8XybJTKQbM/EHNxYjUtD8="
        }
      },
      "19": {
        "private": {
          "type": "Buffer",
          "data": "sJZbPt/uPs4mm5MBIY/vRaxZfjauzmImXRsDKuLTKFg="
        },
        "public": {
          "type": "Buffer",
          "data": "JoEKNcdpSeeMY2xx+p3qqfrdF8q5o/wVn6t1uxsF4Ww="
        }
      },
      "20": {
        "private": {
          "type": "Buffer",
          "data": "SDE+SzGQWzjVbH1qpf7aCBdtguX5+3PlzBTsOq/4XVo="
        },
        "public": {
          "type": "Buffer",
          "data": "BZ1w1aLMzKxtPjbQ6bW+YgsB1QDUxWfdNY4xnh2La2A="
        }
      },
      "21": {
        "private": {
          "type": "Buffer",
          "data": "CCXlQePA1uWjDkLLIL6dbnGLkiLxyNSgha8ZjDju81c="
        },
        "public": {
          "type": "Buffer",
          "data": "+dLwT7RQ9IRn2keIbCBuuTKRsiZJrnPsAqtunK6xEF4="
        }
      },
      "22": {
        "private": {
          "type": "Buffer",
          "data": "qFHX0cFcZWuYg//bXjjGC/xkn9XYNSmFQvQhZn49k2Y="
        },
        "public": {
          "type": "Buffer",
          "data": "2Ve31Uw0tgG8VaPyLZnbFHBPPr93zyylmkykaoxdhHk="
        }
      },
      "23": {
        "private": {
          "type": "Buffer",
          "data": "0BarUZH1/yocTOHhsO8RzJUbekcm/FtkdjNdXJ6dm24="
        },
        "public": {
          "type": "Buffer",
          "data": "exQGX7AVqfOclTq3tCL6gtgX2bW9Lv1wC1imZucVMRk="
        }
      },
      "24": {
        "private": {
          "type": "Buffer",
          "data": "QGzLxH6UxbJmiVcb6R39e+TOLLRrmbUSXOCb0AyK1Ho="
        },
        "public": {
          "type": "Buffer",
          "data": "XMxPN61GK7dO9B/qsrLldjZ1L97VpO2kjuRxHf1CESE="
        }
      },
      "25": {
        "private": {
          "type": "Buffer",
          "data": "wO0MttcBl1YDjiY2BEuO1aO2f6/gbbgKmg9+SCO6gG0="
        },
        "public": {
          "type": "Buffer",
          "data": "6yq0tGXyEwB/wVEGtNPKntFWee+iUuOvX/F9L29+CRs="
        }
      },
      "26": {
        "private": {
          "type": "Buffer",
          "data": "AI96s0l/hIT8+7hZndFXvIbDLkfqW3smpU89dnOSnXo="
        },
        "public": {
          "type": "Buffer",
          "data": "clFZlkz5yAw5YDR0448HG5w4zS/sxfX0u6h+TGJFayA="
        }
      },
      "27": {
        "private": {
          "type": "Buffer",
          "data": "MAKKeqmfuKtxKZIhAF8s10n2rbsHeKFwYIgkaB/F6FA="
        },
        "public": {
          "type": "Buffer",
          "data": "g2ssi7cjYKU2ZA6Ut5eHIljknW2wezK78NbMky4Vl00="
        }
      },
      "28": {
        "private": {
          "type": "Buffer",
          "data": "8HaqQHIg3FeTKKLIKcRXgpaSnLZJ/ygchw9Li2e2q0Q="
        },
        "public": {
          "type": "Buffer",
          "data": "CJE66L9GPQ16bxfRSFhi/PHCrjt5AOzm8radB3gD+20="
        }
      },
      "29": {
        "private": {
          "type": "Buffer",
          "data": "CMigJJeofnPn/KvqvSJTmmU2GSrZumT7W2WoSQkEXWU="
        },
        "public": {
          "type": "Buffer",
          "data": "Ve07c/JDCrPvNANSpNtBi+KiE3G8HEi2wsRUbXzL3gg="
        }
      },
      "30": {
        "private": {
          "type": "Buffer",
          "data": "2Dh7z6mmZaZaULOThxgeYLNpK/izDkkUsabTUQtp+k8="
        },
        "public": {
          "type": "Buffer",
          "data": "WDK1I2tBxck9Km5jawwTRx7FqrDgalpY9xptkZY4vxE="
        }
      }
    },
    "sessions": {
      "6285947674337.0": {
        "_sessions": {
          "BUfRP1R5sVOeQ0qri0Yl05e2S78zDSv5bB21qdmQiUQ9": {
            "registrationId": 715820055,
            "currentRatchet": {
              "ephemeralKeyPair": {
                "pubKey": "BRGLpBYgdbGWMacMYUaqcaCQArzeQEMLjLQw1WZTP9Jr",
                "privKey": "UOwKsA5H6nr9CqG3vR8Uci6NktUrqz9jwDU8lXrW/2E="
              },
              "lastRemoteEphemeralKey": "BZWpYTpzvl5er7IY3dBE2K+zGv4rPhpsG+Hzko6ati5U",
              "previousCounter": 0,
              "rootKey": "V1Yt3+gNZhCDh3EyRKcWfksCSHP4p3OBHMbPh8nE5f0="
            },
            "indexInfo": {
              "baseKey": "BUfRP1R5sVOeQ0qri0Yl05e2S78zDSv5bB21qdmQiUQ9",
              "baseKeyType": 2,
              "closed": -1,
              "used": 1668082603113,
              "created": 1668082603113,
              "remoteIdentityKey": "BbRrfJHWqaG3QuJQsQSCvTqZgIGqOaikhjuto4LgZ10y"
            },
            "_chains": {
              "BZWpYTpzvl5er7IY3dBE2K+zGv4rPhpsG+Hzko6ati5U": {
                "chainKey": {
                  "counter": 6,
                  "key": "haQf41kegWqkqX0jxlcpnlzBar5Q2iBS17ULCblyAoA="
                },
                "chainType": 2,
                "messageKeys": {}
              },
              "BRGLpBYgdbGWMacMYUaqcaCQArzeQEMLjLQw1WZTP9Jr": {
                "chainKey": {
                  "counter": -1,
                  "key": "j9HJXczANSHlafAcIutZf4+Ks6xI+CVDfJehEp1VoME="
                },
                "chainType": 1,
                "messageKeys": {}
              }
            }
          }
        },
        "version": "v1"
      },
      "6283849345181.0": {
        "_sessions": {
          "BRpe52GjqIYyTJi7cDYV5zrBWlupubhtKmGK866bPbN8": {
            "registrationId": 1214760142,
            "currentRatchet": {
              "ephemeralKeyPair": {
                "pubKey": "BfTMSfvVDUvXjxRmeOFb1fN3+GIVCfQvTSpx+RtVvIA3",
                "privKey": "cASAzGYn9+weji1vE8we6PStvW7G9PX/3J+4hpYP0WM="
              },
              "lastRemoteEphemeralKey": "Be4W+yqlLcmhliHPVCq9LwMUehmEYrCFLXvroNazhVV2",
              "previousCounter": 0,
              "rootKey": "ryMeh4DOYNuG+MLuc27CL5Mcr/5Erll6Dej33P6f3S4="
            },
            "indexInfo": {
              "baseKey": "BRpe52GjqIYyTJi7cDYV5zrBWlupubhtKmGK866bPbN8",
              "baseKeyType": 2,
              "closed": -1,
              "used": 1668082618742,
              "created": 1668082618742,
              "remoteIdentityKey": "Bc2TPhjykYZERKmpJgW8cyq+/jEtwkBhSKlsEcdFY9Jx"
            },
            "_chains": {
              "Be4W+yqlLcmhliHPVCq9LwMUehmEYrCFLXvroNazhVV2": {
                "chainKey": {
                  "counter": 0,
                  "key": "1C7KaP4t9UPYD8j8xH/zolxRfQcyabZdXiLBeiKjf7g="
                },
                "chainType": 2,
                "messageKeys": {}
              },
              "BfTMSfvVDUvXjxRmeOFb1fN3+GIVCfQvTSpx+RtVvIA3": {
                "chainKey": {
                  "counter": -1,
                  "key": "RyogtV9ZMNZE3s1Mkc4a72GbBnK/tqhzOjABbAXVMO4="
                },
                "chainType": 1,
                "messageKeys": {}
              }
            }
          }
        },
        "version": "v1"
      },
      "6283121411380.0": {
        "_sessions": {
          "BXTJa4anGEqFDD2QJAOkoU7fEBHyp8krrph8zKoNfHM4": {
            "registrationId": 1792450497,
            "currentRatchet": {
              "ephemeralKeyPair": {
                "pubKey": "BW0K0dUzmTw7zXhAcv68as1BVrgKIdO0tIeLjGt1jm9i",
                "privKey": "cHING3EaHNvnZ5tPK8AOkbia2db/wxlyWKN+VrWknUE="
              },
              "lastRemoteEphemeralKey": "Be8DH23MzijSZsms7VdcPiWJyQwYUeUnuJ/KZF9+YrgO",
              "previousCounter": 0,
              "rootKey": "7Jeq3LJBAk0GulsFUqXJKa7osbF9v9ugVpdrxEneeOY="
            },
            "indexInfo": {
              "baseKey": "BXTJa4anGEqFDD2QJAOkoU7fEBHyp8krrph8zKoNfHM4",
              "baseKeyType": 2,
              "closed": -1,
              "used": 1668082626767,
              "created": 1668082626767,
              "remoteIdentityKey": "BYoTyEmhn2ZlD2VJrHLgSO4P8ScrflmytYgVKqE7Wk9Z"
            },
            "_chains": {
              "Be8DH23MzijSZsms7VdcPiWJyQwYUeUnuJ/KZF9+YrgO": {
                "chainKey": {
                  "counter": 0,
                  "key": "ezg3bi80qGNAVR9LDbi6MjkIOridct8Xxgcp4wAFzcM="
                },
                "chainType": 2,
                "messageKeys": {}
              },
              "BW0K0dUzmTw7zXhAcv68as1BVrgKIdO0tIeLjGt1jm9i": {
                "chainKey": {
                  "counter": -1,
                  "key": "pB77ArUiAPyq5GjaELvfwXxTpdUW1GJvI0nPJ94mi/U="
                },
                "chainType": 1,
                "messageKeys": {}
              }
            }
          }
        },
        "version": "v1"
      },
      "6281213006650.0": {
        "_sessions": {
          "BU2Sc1lvaV1JHIl+PT5BxeRBuYABf05e8LfkC378Za0z": {
            "registrationId": 946024461,
            "currentRatchet": {
              "ephemeralKeyPair": {
                "pubKey": "BbLWg23KrwfyuyreCnqmHNHmXSaVNPWg/wqxTJ9y0zFC",
                "privKey": "kNogw0Ou3uo+3L66CdbQAqD3oioy/4qw0hC4qojcTXI="
              },
              "lastRemoteEphemeralKey": "BWnrvK6DhAdZNYfuHf/gfHtElYR5Yr0UD+cgFe4zFJIL",
              "previousCounter": 0,
              "rootKey": "HQo+HV90mbAEIDI4nMwKVPk4CxJk6ajY5tBDWNe7d3k="
            },
            "indexInfo": {
              "baseKey": "BU2Sc1lvaV1JHIl+PT5BxeRBuYABf05e8LfkC378Za0z",
              "baseKeyType": 2,
              "closed": -1,
              "used": 1668082639221,
              "created": 1668082639221,
              "remoteIdentityKey": "BcPtZ+WQZ/cDq+8A0dMzhuBEFV3wCI78JQIfDZCg0Ht0"
            },
            "_chains": {
              "BWnrvK6DhAdZNYfuHf/gfHtElYR5Yr0UD+cgFe4zFJIL": {
                "chainKey": {
                  "counter": 0,
                  "key": "mdULS2uGHxPUYt8jBWs5OaqIONJv+cXJTC/+FyY8WBw="
                },
                "chainType": 2,
                "messageKeys": {}
              },
              "BbLWg23KrwfyuyreCnqmHNHmXSaVNPWg/wqxTJ9y0zFC": {
                "chainKey": {
                  "counter": -1,
                  "key": "uHn+jBi88czf+qnqNJZ5MOJdJsbs9WOCDaZJi1hbc8I="
                },
                "chainType": 1,
                "messageKeys": {}
              }
            }
          }
        },
        "version": "v1"
      },
      "6285870620735.0": {
        "_sessions": {
          "BY/moUu/oQoaumfarEfe7VTItL/dHfkiVY51U9e2woEX": {
            "registrationId": 65879332,
            "currentRatchet": {
              "ephemeralKeyPair": {
                "pubKey": "BQYLeG5i4Of3GymXFUyGbGolK59XFNcLyrNIrnSXq5w1",
                "privKey": "yKgE1oIBF02SrcdaboUGBC+ozWTCN+xYnoIMtY2kVGQ="
              },
              "lastRemoteEphemeralKey": "BbUh+gbh0ErHziVtCEBSSWSpVH5ywXck1OZS1MTMUblQ",
              "previousCounter": 0,
              "rootKey": "3YW2cAxgYcfcDTGQ7A2dExi3x5VjkNPMuwUfJOukXhE="
            },
            "indexInfo": {
              "baseKey": "BY/moUu/oQoaumfarEfe7VTItL/dHfkiVY51U9e2woEX",
              "baseKeyType": 2,
              "closed": -1,
              "used": 1668082651340,
              "created": 1668082651340,
              "remoteIdentityKey": "BSm+wxWO+QZGasUFhPwmbj2YvCj0hNXwPj0AcQVGSMxn"
            },
            "_chains": {
              "BbUh+gbh0ErHziVtCEBSSWSpVH5ywXck1OZS1MTMUblQ": {
                "chainKey": {
                  "counter": 0,
                  "key": "MUktggHTvaDJnnwc8IEetUpLauTCbICNPBltguDUZ1Q="
                },
                "chainType": 2,
                "messageKeys": {}
              },
              "BQYLeG5i4Of3GymXFUyGbGolK59XFNcLyrNIrnSXq5w1": {
                "chainKey": {
                  "counter": -1,
                  "key": "FHSWtJ9G9HxWhaf2Bycx3jRhhZPsmax1m3koUyaeLcQ="
                },
                "chainType": 1,
                "messageKeys": {}
              }
            }
          }
        },
        "version": "v1"
      }
    },
    "appStateSyncKeys": {
      "AAAAAPTh": {
        "keyData": "GEZC82c9uJPNOZ4LNNdY5k47hT60+ZiicR6y03zGTzk=",
        "fingerprint": {
          "rawId": 1297199365,
          "currentIndex": 1,
          "deviceIndexes": [
            0,
            1
          ]
        },
        "timestamp": "1668082603997"
      }
    },
    "appStateVersions": {
      "critical_block": {
        "version": 1,
        "hash": {
          "type": "Buffer",
          "data": "VgupG+vJ/e4rAG/fMae9UvF4J/0WOSqRaL/vFosSx0sHsUE2j5a8i5m4bgVjKI4FmMBbXwDzPCInLHk/QvFFC1nE9HjljyrIcrm4vs9c9cmy6WB74Vrl0ry7/Y+AvUr41GrSmWcyI5jMUWl+QgxmKrRjusshXwfs7ziiipA9gmo="
        },
        "indexValueMap": {
          "N0fLWA8xFZdpzEQJMgOONB2z9Y8oTBX1bVc4C9vXDHo=": {
            "valueMac": {
              "type": "Buffer",
              "data": "JIS+ital0oUiGpTCilwPwwzMpaFp1+qtgyLnXAO9bAw="
            }
          },
          "nEQo4tf0C8we/L3k7qeLdAV39NwjzDRCrnwjC/023r4=": {
            "valueMac": {
              "type": "Buffer",
              "data": "r52sxJScZNYM3sf9o0hxj07wkXH3WSKvAErPm7aKJsQ="
            }
          }
        }
      },
      "regular": {
        "version": 1,
        "hash": {
          "type": "Buffer",
          "data": "jG8xbfwn7gk332bV7wWxmyR6uTklgac6wObVi2EhtBqCbAy4tNx+Za5pXEZP3SeM2af4+w44O7veGBC8wfrbKikRyI1z9UtJHEbHgsw6Bw8AlzHOGCRr1thh45sEL88ewmLKtnLxddBrs0fzzifSt7/z1Pbk7uYnMaVDQQUeC5s="
        },
        "indexValueMap": {
          "JJCgZgPBCCPpNMYswU8ha++lyNrySIKcopAuZG9doIU=": {
            "valueMac": {
              "type": "Buffer",
              "data": "87/ESIETNxa5kW12tIqMTXc5hj6UegJTM/iihQwbCb8="
            }
          }
        }
      },
      "critical_unblock_low": {
        "version": 1,
        "hash": {
          "type": "Buffer",
          "data": "K/EtijJ3TVGX555fYc6Gdce0d1/7tnwDQ1hRmb8E2JcXLj5brrI2HiLicez5yrAjc8l8BwJzrY5LZ6Rpw3fwjaiAJVMCMXapX6mPMXQaVVavo/a7O60T0+d1Oar0cRHX0zaFATFZs4UvFvWjECwGENofZJOleHitNlh8SZELYPI="
        },
        "indexValueMap": {
          "Va2sQrE86eDbjfxqXRcITPjo0VPNXJ1QuAmXo1hpfzc=": {
            "valueMac": {
              "type": "Buffer",
              "data": "3GC/kRTcD+k+9AQ29LNso/1qiONUk9RPywhwCyV6prw="
            }
          },
          "Y23UPgMrA8v6BRu8jIZgHHuYOfT+MXB4Gt5QfBisC/k=": {
            "valueMac": {
              "type": "Buffer",
              "data": "O24quTt+yBxMI9j0QHK6RMIGRUFaEFEem7Se9SFjteU="
            }
          },
          "cnBn7HlHofP2VYEdqv1nQs6wWk1iqx3C4L9zeBh6q0o=": {
            "valueMac": {
              "type": "Buffer",
              "data": "bE0rC+1j1x2vQA48nDe2hTHAOoxmLYQfQlHu1bmjFSY="
            }
          },
          "pp08X1arGTM+LSJOX2qqEqTsAWJd4hdSGCXlWvRpFH4=": {
            "valueMac": {
              "type": "Buffer",
              "data": "KGrBWLKiXSYsOUyrb9xwk8YkiXQ+a7Mw+T33nsiPOVM="
            }
          },
          "qS75YkLqMJ4eSIU3VuqyCEhLntfk0QKG2MN1kxX318g=": {
            "valueMac": {
              "type": "Buffer",
              "data": "7sMRRy1310iFPyLb7Hj2YVaUbX3d5I53SBK31hd8v90="
            }
          },
          "F9BHCn2Qp8yYrwZ/KLZcE/tA8zATNKd5f07SI2IkxtU=": {
            "valueMac": {
              "type": "Buffer",
              "data": "r/FLmbm1/nSZpjPPrFFV98uBYuWxv+cJgJ13XM/3Lv0="
            }
          },
          "1M5FRcopGzBntGermHNAlRLPJ/6mArR8i1msXH90sc0=": {
            "valueMac": {
              "type": "Buffer",
              "data": "You94b25pwWuJyCfrUSrpkK9gjnuSO1Owvs9K7bLqbU="
            }
          },
          "A4TS7i0qnFPdW3TxWbD2xYr+MN2sUUH1nwoZyQ7snvw=": {
            "valueMac": {
              "type": "Buffer",
              "data": "rBBeKmSXj559LglOHtwxSQYBncj8xR875upIeCPHywo="
            }
          },
          "NDVItB0sneUemJXTkqrcKmQSB4hJ1LnxxQ7o61Nz2AI=": {
            "valueMac": {
              "type": "Buffer",
              "data": "ZKDykn5nhS943+cGrVaTJdcXpkT8Y7oCq3LsnvkBURs="
            }
          },
          "XTtT3vuYgYxsBbGL0V76sakNXgINnHwO52yeeHyQxz4=": {
            "valueMac": {
              "type": "Buffer",
              "data": "9Pl9dcMmh17eWe29vl9mfv4Vl1kf+7gmcRPcVP7xSY4="
            }
          },
          "zFOcvIIveiimqFo+mtOfowOtuRVYbuM3YeeBgHOeL2k=": {
            "valueMac": {
              "type": "Buffer",
              "data": "CNZtP+xUtmamyfR9N+s67bb/1SG4GK1zddZWKbqCVWQ="
            }
          },
          "rymWI6Y5omZsDzU0BOjDvwTdxiz/3x8wS3qFL2/xaAE=": {
            "valueMac": {
              "type": "Buffer",
              "data": "YniviTUGc1PS0VWP9fg9UNLSNvGw5BtEweVp6IlaxDw="
            }
          },
          "KaS0QOLCgJg4wXJ7juYeWyhnSxmPKW/TtejBZV/Qyaw=": {
            "valueMac": {
              "type": "Buffer",
              "data": "gPC8DQO1ztqUkYPUAzs1+j/HQ+wDs40noypX7xew1tU="
            }
          },
          "L/MVNfAX8TJrFccnlVzRtGsqLexOrVEt9glX84aN8iM=": {
            "valueMac": {
              "type": "Buffer",
              "data": "BBeOOBvFbb+E32wacUsxHSHAY4DdeykYf4Z7FOtKT1k="
            }
          },
          "G2DVAwVzg6X4L2pMe1FJLuqRWZPBie4dUJSJfvanabs=": {
            "valueMac": {
              "type": "Buffer",
              "data": "1EE4VkCBm/4dNZRWCF24VXXJ8o2lonQpiedQljEssTo="
            }
          },
          "csh/yR2W9EHGck5AEUBhSvgFsr1LDLlUn13hatPTTcM=": {
            "valueMac": {
              "type": "Buffer",
              "data": "LyjrVGmBkyrqPSvHwUh5XROyyhNuNnSAI1+b0HRHct0="
            }
          },
          "RwSFU/pudiFicQV5f968mvTzEbTL2AdQ6hBF0ccchEM=": {
            "valueMac": {
              "type": "Buffer",
              "data": "U3J4aBeHZ/Hr+rgM/TI7S5NcC2903xYe7BBtYzrF/nc="
            }
          },
          "V1hFwYnbH4k9QwHm8hJqRH28C894V8LzZkA/QKMBoIU=": {
            "valueMac": {
              "type": "Buffer",
              "data": "Je2CrhLrh7g9Z6ggpBKT8w31N85zZ7F+2qci6sXlySY="
            }
          },
          "YQEARElTwI/cVCsH/k3NTfpJTaq/gyGcJth2d97tRfg=": {
            "valueMac": {
              "type": "Buffer",
              "data": "Dmhk8Vz07OEE4IAQtzQRUf3l3ijaGAdPO4ZFW5KNab8="
            }
          },
          "TQ9Gpp9CEGomKN9JjyIifhLqaPdyiSPVdFuTv5dDgYw=": {
            "valueMac": {
              "type": "Buffer",
              "data": "x/jNYl7asp1prG6H18h+ZIx09ASzUzQEEmNiCPdKZjo="
            }
          },
          "tGqFQC7Nh6ciOZU19y2ICQyJIGvC0D5rmKok2zHznIg=": {
            "valueMac": {
              "type": "Buffer",
              "data": "rcfOyTS1UwkJs0UL/ifvVcwjPsmgCCZAw6p2KKsJt/Q="
            }
          },
          "v0TWkrxmfu2I5pvhls/JLTjVmJa1zViCTE/JGKbTaWM=": {
            "valueMac": {
              "type": "Buffer",
              "data": "xX7I9CgFKdmIVwA+D3RF6bTXsLxS+HpggAai6W1Q/kk="
            }
          },
          "FzsRIdaeaLNiiK85rg2gmPhZJbio8mHYEZbuELgdDr4=": {
            "valueMac": {
              "type": "Buffer",
              "data": "AjYBEgic9LF/6fH++AN/0K2hNN2hrLofhp2xWYTluxs="
            }
          },
          "fHMCUNagiH97gs6pv6GdVFcmtY7gdTW5BbD6ikSxiTI=": {
            "valueMac": {
              "type": "Buffer",
              "data": "d3KEPVEZrpCF3d9oXeq2r+WvKIOgQexGf6ALxOHS6Qw="
            }
          },
          "C/JpSgAbfe8SdIUBNsa+wf8ejzhEJxSLa3jMiq9bXq8=": {
            "valueMac": {
              "type": "Buffer",
              "data": "nyPaD0+KZlCUOrGiMb6N8zKxocz+MttGCVC1F6FWGp8="
            }
          },
          "4Ojb3gExEivMOCFm/BP/r5sPkKyyzjfmqjUaV6rRZPM=": {
            "valueMac": {
              "type": "Buffer",
              "data": "PmrK9Q7p5KE7BrVk5CRdZeaCLMerkEzY+hB2h26hhZ8="
            }
          },
          "ZHzW/z8T9xYUmic9QuRilV/oiQoQRJ7T5op+h9ErJdQ=": {
            "valueMac": {
              "type": "Buffer",
              "data": "hSCPaLUab2+q6AKQb2EwcNpmmEimC4kPff938vlLMqw="
            }
          },
          "XKXQLN9FTE30HzXY3l+uf/MBfx6OjnEGTiqo2jr0RFs=": {
            "valueMac": {
              "type": "Buffer",
              "data": "mRKE5m3A8ka1hbZ5l5iaifSSEuBGTWtqYFL+JhwZCFo="
            }
          },
          "331GHkUV22MDM5jgE+XgrF3mM5nMiSw0soSxgV4qseQ=": {
            "valueMac": {
              "type": "Buffer",
              "data": "yR+uEXlnsP4dvATHA1YkbrcaMW/xdGbEE5JrkyP3P6Q="
            }
          },
          "K1b8KeZbQ71+k+fhgFC3C1gjyg4UM0IdY23E3sLUCBs=": {
            "valueMac": {
              "type": "Buffer",
              "data": "S83TfzUjYFG7ZfpW5UwVcj8QqF7q3g659aVlm8Lt45Q="
            }
          },
          "QzKz0krbzCriI6Weitp46TIQY85WzSXnGIOuTvyOzTg=": {
            "valueMac": {
              "type": "Buffer",
              "data": "r654eZgTRV7IUzZtmrU1O95EFWeHGSKm8DSGNqHMgCA="
            }
          },
          "LMfHte+uo9o/mrnFGpYwbPikXsw5kHkXZ8RABXSxrZo=": {
            "valueMac": {
              "type": "Buffer",
              "data": "zVqkwiltbVeXEez3vI6x5WTECviFXhPnQTn72LtcvQQ="
            }
          },
          "ZTmSkKuC6LeIR9r9Fhy9QErvRsZEshSwc4jEGgDkKTM=": {
            "valueMac": {
              "type": "Buffer",
              "data": "gMG+PSWRk8PApa8AoJwZNMqLO8yMsASSsGllSUcLpcY="
            }
          },
          "B3wfMi4mHmumYeUpZuZShLmJyFDuhbq3zYzJzBzQfTw=": {
            "valueMac": {
              "type": "Buffer",
              "data": "8QD3rTYMqMGwayZBoRaSNH81KumJHRozR1Rx94jC/yo="
            }
          },
          "9pkECyVqd+fpNXqA/zUDzAx/ztDJa+Eqs4x/YIwMJKA=": {
            "valueMac": {
              "type": "Buffer",
              "data": "xUmFZb6sAIH8+zlF/MnRLo/pRmBnuVehRbZ+stqadGs="
            }
          },
          "eAziKiLdy7Y4S6WXNO0mpltnvfWtJUMCekGTUw+Uu8o=": {
            "valueMac": {
              "type": "Buffer",
              "data": "011X2xBg+jOWLY/wDzMcsg+z1K77MtAitIX8D0s1UMY="
            }
          },
          "yrcmE539thZl/CbssPYEfth0Qwuhsmmrtv9VRQn7a58=": {
            "valueMac": {
              "type": "Buffer",
              "data": "9A5Me/XVN9j6uEeuw9NZ8TDcKRbLqXysiiRUt+ws7lE="
            }
          },
          "0Uk0kDkVuzVbtVcjDI9vRWYtNEzNP/SwcRNhIDaVeqs=": {
            "valueMac": {
              "type": "Buffer",
              "data": "WCRNLgRyA5Hd3W1jzyzWvQC2hx7TQKZu2Lyi/n8Ig6s="
            }
          },
          "JvYmejYoXsJ4kuPQiW7py+Gst8NoVynPoJro4egHZr0=": {
            "valueMac": {
              "type": "Buffer",
              "data": "+4pFjfejd98TtJFm2jahNqSAFzJ/arz8Ufh2TPWcvBA="
            }
          },
          "fBv3t09PJ2iMF1dSlQV6PbJ5gq4k0W8KGnsXIKTsh4Y=": {
            "valueMac": {
              "type": "Buffer",
              "data": "A5pNP1JRETnIukXB3XGogZnZ39J2M4EOUlOoJG7/Z50="
            }
          },
          "xQ2EivMZP6zZ8E7sijSvD3m1gZmcJWx/UK2QJ8eUR9M=": {
            "valueMac": {
              "type": "Buffer",
              "data": "YIRApxb0a96nJPFJ/5mzFVsIRUa9EFz5g74mBeUu81o="
            }
          },
          "lxCGJv7yHZJeGSpV/XmgHYc0WScU5506Nf8NtN7myVU=": {
            "valueMac": {
              "type": "Buffer",
              "data": "tB6E7LLe5TgTnvUiSfhZpbujy/24Os/lY5nuyUCH1GY="
            }
          },
          "u8vGOgWRB4gakOXU12bk0TDZofSWCaLbdA+hgRF+gpE=": {
            "valueMac": {
              "type": "Buffer",
              "data": "KUN+4a0vYwH6nT9jZOq1Sosw2hvtLKROOnG0MZBOKBc="
            }
          },
          "dr7Y9G5cF6RtAPfeCMJYWCjfzZkgdCV8bg1omwgSDrA=": {
            "valueMac": {
              "type": "Buffer",
              "data": "4mCepkXtxPuCCnEg/TnDWzgy0YsUw41yEN67805tkWk="
            }
          },
          "RsNwHGdCUlA3WvG/FMI5AajOWtSoXRrkhIyf6lBNqf8=": {
            "valueMac": {
              "type": "Buffer",
              "data": "uXyTuJZVfp/mPWGzGrSxDj2X+nI/zVyTvaLgVFr+ICs="
            }
          },
          "Mlqm22jIk6iYumPCNkTKJjOXDxPpKn3PAs9pxrzS2ho=": {
            "valueMac": {
              "type": "Buffer",
              "data": "NFcho9GmaZXGA1YvS5fEgSM3619No3rjO0lWwepq/Es="
            }
          },
          "xaYh1ANErt/+eEWZSZylMTa8xzWg3jsbkg2314jYWuo=": {
            "valueMac": {
              "type": "Buffer",
              "data": "+CIuIRtUyQE+q314dm2TNZD5rYDaKjhqQjywtvMJ/AE="
            }
          },
          "AKO7AC58PitY3OYQ6mCw5kORmxvuG7SQGAPoGCTtlZ0=": {
            "valueMac": {
              "type": "Buffer",
              "data": "qB6TG2tmNH6RIE5VUX+m47z65yOTv2M3coejXwST06Q="
            }
          },
          "OEvM+Co1JvYuX3QhXluesl4Yx2e9A0MzgkdqklUaHWc=": {
            "valueMac": {
              "type": "Buffer",
              "data": "xmfuL70dh2YBeFidFJ7SCMuZl5N9K0rnXbVXvkOnuxY="
            }
          },
          "/sNuC5DOJ/yGFtPL8m3hMKdCfm02yCBOgF5y++6E5uI=": {
            "valueMac": {
              "type": "Buffer",
              "data": "Oxr5ty3xa2xgkDT8M+pmSyNL8nF189nOJgb32zC2MPw="
            }
          },
          "w4MVlMpTMm6d7zvGsLmwwG59lppxOauEuJ4srr0j0c0=": {
            "valueMac": {
              "type": "Buffer",
              "data": "5hNyf0YiLpTNJ4SuIiEd10gJOW7w80n29kv4o/+Znd4="
            }
          },
          "3FYRvYHsGzTCn+B9bVzuvi+HiWK0o2V9AYLgdRGptgs=": {
            "valueMac": {
              "type": "Buffer",
              "data": "OkWxLmGblkEGv4dEon16+f2ZzojNYa1G/AAx21jyaJs="
            }
          },
          "ZBunm/AYdE6RigryGCGi11NJhvvGLy2gy0V8He55Hns=": {
            "valueMac": {
              "type": "Buffer",
              "data": "yHqTW1s4wac8k4+ibG2Q8374hOcBlJ142h7+QZFzQt0="
            }
          },
          "ztoj7ZWUrSq9K1LEgsHIhuY6m4VBJk4kEHdgW1YVqCE=": {
            "valueMac": {
              "type": "Buffer",
              "data": "AFS/hNJpNas5xQBzwNIPC7TdGkAwyY6cRLayeSzzS+w="
            }
          },
          "9wl67wzxnoVnnO2Vp0zLWeOzvjPuD8/gIaQa9MxIGto=": {
            "valueMac": {
              "type": "Buffer",
              "data": "5DOhG0c0oWnnIqq6OH3hwsdaHm/3ipSFWIKhXhWwKvg="
            }
          },
          "HtsjvPMsKH2BOWFlpiCogJ1gokRXICB2k/uSHRZ4sHE=": {
            "valueMac": {
              "type": "Buffer",
              "data": "fROby8U9QZJcxgWTKIy3oXXBbf7kBVgVbCkIiDekkOA="
            }
          },
          "FSA6mCMvVc3wAc0ifSW7HdRYuT0mD34VP6trv6EW2JM=": {
            "valueMac": {
              "type": "Buffer",
              "data": "hQvz/Y5Qi7N+PH5JDjmwHNksTgpewISvVJBk8wahCn8="
            }
          },
          "KT4ck+7JT3VFTjvk87lR/+q8ujhs0m1DAKYsr0wx9uI=": {
            "valueMac": {
              "type": "Buffer",
              "data": "S5BD8qlWacwvsMkzsrgJ0uqFfdYTtkUigznuUaivznU="
            }
          },
          "r/udbKzx1K5oFhyZeYv7XNHpNTAGHzWZy5+iBsdPl70=": {
            "valueMac": {
              "type": "Buffer",
              "data": "PEXwnImmWpdz7L26C+3cRbCZO0Z9MXSgO4wASCXoPGM="
            }
          },
          "OZceZcpLtKUwq7EaqeC92ksMH0wIrE7K0n7d/jRDFNw=": {
            "valueMac": {
              "type": "Buffer",
              "data": "DOTPBTxXzFWjkCNMkgvMmdhO36X7bBGhlly4Ik96dUs="
            }
          },
          "CdXsoIridm/oialcbFfe4HvQsMQv2xUKVUeZMKmk7k0=": {
            "valueMac": {
              "type": "Buffer",
              "data": "BZXOH3t2ZrGpp9bd2cirQKpiOHRll13epwvJKalFCf4="
            }
          },
          "nrMPVRd5EHuVxUpCCXLiqI+Le9nG7ibyjBQC7m56P3w=": {
            "valueMac": {
              "type": "Buffer",
              "data": "lKNAFtnI1ZBizS4VglgiZxOyIExJH58evnh484bJLBg="
            }
          },
          "QU5VMaJE0H3a+1ExfFqL4NKL4fNDjYsUMshvhVoz1lQ=": {
            "valueMac": {
              "type": "Buffer",
              "data": "qtQTxYdpWfQ+7ccSFMZoOH3zkWMCjEPLh4+CtWYPg8Y="
            }
          },
          "DDlSHMyNwiD5kxhNniAYXX6pNF6jsHQrOBZF3USfFpw=": {
            "valueMac": {
              "type": "Buffer",
              "data": "MJiv0imLAxFgFXu8XRxoYeHEGhLEmow3FwTTyg4xTh0="
            }
          },
          "TBYYvvA1MWWwNf/BTk9L9yIBowD1Ja9orl0Daj5lSAQ=": {
            "valueMac": {
              "type": "Buffer",
              "data": "YXZhTrBN6v3xvplGDMSip00/O4z2x1vbqt8sDwIYPE4="
            }
          },
          "70wfk9JWGBNo0VHEozjiU+clZsQwSMbjaa+pnAQTNhc=": {
            "valueMac": {
              "type": "Buffer",
              "data": "1e7JEgnDlymcG8a2ceY+Bkd6PrdIC0x9v6e/8VEIVD4="
            }
          },
          "P6Gq/PptI+vTaVkIgOSuMLwIiZ2LKs91jXmdNmtxGnc=": {
            "valueMac": {
              "type": "Buffer",
              "data": "aYGti3xISmzcZwqQvaRjaqEdYKZFUwtSiEkXdbetTPc="
            }
          },
          "fjDik5NRrKLDk0CNR4OcWdeRL0q6aYzdq0tc62PdMCg=": {
            "valueMac": {
              "type": "Buffer",
              "data": "7lksnB+Pdj8Z6F8+trSBwd7vTXK0dxuzidC7hgfo3wo="
            }
          },
          "zrtKVJSD2K0orik61fnQQBJkcWIOVlDH8i/GfEVyR2I=": {
            "valueMac": {
              "type": "Buffer",
              "data": "QnX9xPdmTcjnliWYvpVgiMl2MjhSQKhNrsil0bg5ZGU="
            }
          },
          "9MSkgTPzVa77JunXiElvfjthEmcPmU4J03gYXX6uPk4=": {
            "valueMac": {
              "type": "Buffer",
              "data": "sqOGgPvpd7UNLm5yMG5qybFZBrCaHkLOpRFTH9Rpklo="
            }
          },
          "ihWceVhrQXjOKiLAG2fHpqzOCKZg2su1WD3PifX28rQ=": {
            "valueMac": {
              "type": "Buffer",
              "data": "oiSsB040KG/sEK/BlOmlg0hsP0C+fqIdebobkj6yMH4="
            }
          },
          "8tY2wLAPsz+vb9ux4S5E17KcDyKtx2G+fq8+S5apvrg=": {
            "valueMac": {
              "type": "Buffer",
              "data": "HYSvu1Q0aZGXvIgxVcq2+RTJCLDeOtcK+BV+WSUqofk="
            }
          },
          "49k9FZUUAAVUb8Ogg31TAa2HwjQVDDegXKEzlJrMaP0=": {
            "valueMac": {
              "type": "Buffer",
              "data": "kdaBps4/zVYrHT8jMXTjF4yJYaKUpN98rT5W0Ew8K/8="
            }
          },
          "q/cstt5qL2yQipwmrA3dcvBOUc0l7bReEQMmbRTFRok=": {
            "valueMac": {
              "type": "Buffer",
              "data": "P5DjQsefoURtO7KTsFfEVd/wgkltQXtJxasC9wYjhWw="
            }
          },
          "pp7sp7jwFTEykY0L7JBpX4Tp/9QcAvAEjKi4HJ7Cs1A=": {
            "valueMac": {
              "type": "Buffer",
              "data": "Pzny0PCWfAmy9uw9MPKPeydWrFkSDNYO4xkplyyWCi4="
            }
          },
          "GfsTl+laNvixuShqX/w8xPoMN8zVm6/FGnO0o4oZARk=": {
            "valueMac": {
              "type": "Buffer",
              "data": "0R/GUyhbwJPW6Vs2MzQoyxG1y+OVV5dtD1UiZjr+5aI="
            }
          },
          "nbFB76XOYaCeIgg9HhjG3pnc8Bjjh+fAm1N8nXAR78c=": {
            "valueMac": {
              "type": "Buffer",
              "data": "nrLPBEiMwlQY2Musn9sHPSp6E3wRG8HZGbTPHh3k/ME="
            }
          },
          "uU+4RPY1UH2XsZK1qgh+g2ecRiLIrk7Gi0N8/5MDr5U=": {
            "valueMac": {
              "type": "Buffer",
              "data": "UwevOWfxhYNqvHhwA1PJAkD3lY30NDPLeIqh7SsWAX0="
            }
          },
          "q97rF3Rb4d0kJM33rLbv9OzMgOZEusSxylElED3RDqE=": {
            "valueMac": {
              "type": "Buffer",
              "data": "nWch/Ymzd/F5SUgDjwH0t9xz9tRWeDB7jGB0ZgBpucU="
            }
          },
          "HmThb1SfW9TD0r5fUdog/n3aCeJ8kg+MWdWEh2TFo3E=": {
            "valueMac": {
              "type": "Buffer",
              "data": "tsoy6FmaeRzVWVPfIM7XxKo03gutKFKIe5G90cv8TMc="
            }
          },
          "xaZhBg+T2Wro2eOjJK+rj7ASJ0v/dDN6nnkM3Igue8I=": {
            "valueMac": {
              "type": "Buffer",
              "data": "mRImDh8LAXgAcs0hyXs/C1F8iz3NnVLb+VlZXV3BcnY="
            }
          },
          "hQBgyxE+xzjQfAj8eNIwBOWNburAxU1aGOlcEMBrOJw=": {
            "valueMac": {
              "type": "Buffer",
              "data": "iVOWEd0iYN5w+7s3ZzzC5MFBVnnGw13BIh/Qzm2caN0="
            }
          },
          "VjBo5pRvF4lWabEdrJd0YtWzNFro4wxHirCcvsvt7oY=": {
            "valueMac": {
              "type": "Buffer",
              "data": "foGuUW3jJkixYJJiOk9CcoKzhv4kUSGtx3MwMO3hnY0="
            }
          },
          "8ye/qDUgsttHu5i7AovY10bpCH0J2xOjVksoJwHYCRo=": {
            "valueMac": {
              "type": "Buffer",
              "data": "yBXzxxzTgPLqsZgwwDq7Onb9WNhrFprk8iobcHRG5gI="
            }
          },
          "k3TWL3/N/du08Z7IrXRCH0H2swUzO5D7wSjo+VR1h68=": {
            "valueMac": {
              "type": "Buffer",
              "data": "Vgu1D3P5LrOoxjgzNoeQdyPkBgSJsX1xtHfuVnVx/2o="
            }
          },
          "62ri7wCvBawym89fkjDXKoYoxokpppqDpgRyzQihjyw=": {
            "valueMac": {
              "type": "Buffer",
              "data": "hyWtZ9V+Mujde4YztQuWEf6I2pAiFUYLxrUvqKhjcjQ="
            }
          },
          "fMjzH5anBnfKmNJlGFzQL/NWoDl/Q496/IwPppUxrPk=": {
            "valueMac": {
              "type": "Buffer",
              "data": "kuQYu1E6/OGuGuFxDsYnhCzKDVchPQpn2QUbTeOEDLo="
            }
          },
          "V8LOYygQL5AOMGQh+qR5dBzTMVMc7s5jlB682ogcMHY=": {
            "valueMac": {
              "type": "Buffer",
              "data": "vKNSPoFlfrL7xsVFsklVG2bHjhzXtWDW383Wqs1mq3Q="
            }
          },
          "ltRkfaCyKNxhsvRN4Molo5WZSHhgB2dl6bdbYOaZhZg=": {
            "valueMac": {
              "type": "Buffer",
              "data": "LUSQN2sKf2yJlSXHBlYJxqMD384b/PDuJd5/hui29Qk="
            }
          },
          "4sPb3+W0kanz/YOvDM4idwxtjgq/OyGDrCChSPKnqAc=": {
            "valueMac": {
              "type": "Buffer",
              "data": "h9IevajPsxF0Zqud/QVp4s7tUIkgOmfRgvkGwmP3bTM="
            }
          },
          "1FG/bRN/pN/wEzOvBB9TVa04YQLA56q1rbHVWeNYo1g=": {
            "valueMac": {
              "type": "Buffer",
              "data": "hso9SJ2ijS12Mx1zAkVtdxu8jbHeq43s4PQTFk4V4R0="
            }
          },
          "qoBpVo0Rqn0BMBi4Ngji4+ffwBR/Lti1E/Axr4LDvcU=": {
            "valueMac": {
              "type": "Buffer",
              "data": "PUBlkQewVSTptZGy52D6ZHzGDtgspmwYJx5mNYPCujk="
            }
          },
          "f8M0Yie366B6iWs+hXDkJDlyETCyFdq9sjkoQ7VEDT0=": {
            "valueMac": {
              "type": "Buffer",
              "data": "p1IUL6W29K57fDnC2Iqv1gBh8JNWlVW8YJvdhsEq248="
            }
          },
          "BLab4/w3uVJ5zk2fyi2GW1hluZkHarklXeEFX+fFX0I=": {
            "valueMac": {
              "type": "Buffer",
              "data": "ZjI30ptFJrHRLEOd7nF/dNlStt/5REwHYXl98Z2NxZM="
            }
          },
          "6juyB8+KysfCfUvGurGk4q38SoSaPjkBSIJSKryS+n0=": {
            "valueMac": {
              "type": "Buffer",
              "data": "VInZDY/KCtCXaFoXmoSiHrkGZvAEV8W5MX0MEy4XiUM="
            }
          },
          "pEnhZh3L6rZGb3K5YhQRYL4yinRpbjfJgZAy8Wwpc/Q=": {
            "valueMac": {
              "type": "Buffer",
              "data": "EDY54ZSKLV9b/b3OyVAwkgSTVfbN4lOpdvGYv6EfGlg="
            }
          },
          "i0X6qSNCllOKMeNhGPrZaOpr5ujB4x6h4isFPtbXIXc=": {
            "valueMac": {
              "type": "Buffer",
              "data": "H/0Hzhkuz0bWSyBdO4CaZfTaKjzsh5BTc5q1gPUqpVk="
            }
          },
          "cT+50mFm3lwy9bx8LOygViw2SMURmVTS4rEyE5X9eWk=": {
            "valueMac": {
              "type": "Buffer",
              "data": "xFzVO1/O9mdWygaCDUeiCSYJlun3mQSCBMvQGQC5sOw="
            }
          },
          "n7Hiweul8XZXNc0Dsxq4KqOY9ztjT0wwlpxRStPNNsc=": {
            "valueMac": {
              "type": "Buffer",
              "data": "4G1HlrNZ1vTWtGa39MG7aCfbL1dtaUsAqU5QtHOWQfs="
            }
          },
          "GIPwDpHDp+FF+8INJDL0DJIre6b9wzD0uaThXaXNeVc=": {
            "valueMac": {
              "type": "Buffer",
              "data": "tTc7G6nzXaj4lx21TNsOqZppsyhg00xB66U0kCk2k68="
            }
          },
          "9GUJWUODD0gG7EOMfj1By29kTDKTPPSfIyg1+TIv8kw=": {
            "valueMac": {
              "type": "Buffer",
              "data": "5zS6Vt/WdPi5sxwab55N0A9mGNmICROhmwrXuo8sKOw="
            }
          },
          "CoyJ+x3X3yN+SBVBeuasHqd7XXVIJZ8XG2dMqHFi5Cw=": {
            "valueMac": {
              "type": "Buffer",
              "data": "UJW6UxSmf88GzYSPhAp6Y8KkxA+jqkdyEO+Zh2k6Bsg="
            }
          },
          "2ZNYcP5o/H5ms1FFsfn2TYmL3Pgjhf5bVSO01HDNIzw=": {
            "valueMac": {
              "type": "Buffer",
              "data": "7U/ueAHqKfZu/CRfIyRGZYImy8TlPZnFXdsqRJupEEA="
            }
          },
          "D+Hg0P+ClcqqPJPil/UOeLedAMfpEzOrQNiM8LXEYE8=": {
            "valueMac": {
              "type": "Buffer",
              "data": "Qqxdmik/NzTc0tJb7PWEJkiiqVja9pqj6xLfsnOEcr8="
            }
          },
          "1aISFdL6NP32vXjhMUD2fbJtQlLkMBIZGlspSSjKPT4=": {
            "valueMac": {
              "type": "Buffer",
              "data": "HfZq482Tp1PZDLHZbB7j5kDZEyTgsRP5tOIwF2IUEYs="
            }
          },
          "8iNoc7SrbwwlSp3Cx5Dzr2y9Pwd2EGMT/H3XaZSb3d0=": {
            "valueMac": {
              "type": "Buffer",
              "data": "KzK4HrCGJi7R18lr82ERj9HYcVuETug3selIpnugcXo="
            }
          },
          "P/nXd68p61h3fPI7fwE2H/exTVpx7K9pDjma23pGm14=": {
            "valueMac": {
              "type": "Buffer",
              "data": "BqzjqvamIPBlx7hxsNdzbSPeI1SRj2h4Igg7dgeLQmI="
            }
          },
          "9ylyBBcKT0C8jxgk5XXBs45lg//+2UCFOZ4WqZF4bNQ=": {
            "valueMac": {
              "type": "Buffer",
              "data": "zGS7Z+2ZfJHF3vjmzo3B70LIsHymJd1t8O1a30KeW3c="
            }
          },
          "zjB+XG1Rgy4N1Vbz5cUMPIY6LYSrOL+L05C0s5sngbw=": {
            "valueMac": {
              "type": "Buffer",
              "data": "Vw21axczFZVRlexwufXBbfnK5xDN0/fHSPbx1md5yWM="
            }
          },
          "5ZWmQa291wYWuujDHrvCD9w3e+t1eP2718CESGpem5o=": {
            "valueMac": {
              "type": "Buffer",
              "data": "RPCnrbmDTVopVbD8GM0uZDlfqv/Qyy/kaf0cEcDBw3o="
            }
          },
          "GQsJvojB0RHiXDF6fqD/MeGA8hXmwpf4X1SmiBb8z1o=": {
            "valueMac": {
              "type": "Buffer",
              "data": "jrDLaW4+yQGX9IfuR52dMs8APoTQh/DFAqLZuOFqfc4="
            }
          },
          "Yz+1zFXdBZyYZIdoNWBrYkndsBmH391u05KAT69Hnko=": {
            "valueMac": {
              "type": "Buffer",
              "data": "fTcQZ5tGe2n6IolXJgfo3HzoiXKQwXk8KBbaeXSB9Ww="
            }
          },
          "3BNf8umXCMEWU9ZPm0ZeSnnJ/RFvshVMhDWdLQnh3EM=": {
            "valueMac": {
              "type": "Buffer",
              "data": "EKa0QSb7ahy8GN9WBrr7WbvqRDwh3fTyjyF14MMPc8M="
            }
          },
          "l/IHytTh7IMR4nIHFU2SFulSLnd6MSQTR7m4/16J2aM=": {
            "valueMac": {
              "type": "Buffer",
              "data": "5klZJqp5lom/T7ZbD7UZTc8Z5phy8r36qqZ604QR7UY="
            }
          },
          "XzlQhX/T91hnst+1vYKRTqlwbJNSskfOpojPmj5Z0y0=": {
            "valueMac": {
              "type": "Buffer",
              "data": "cSUSAVAlbm1cUV1IsyeJTCmYIhAMKu75khvvhLgCW7I="
            }
          },
          "jnz/T6sJswS3nebX1IZJKZVx2NDHWRlODMnhj3LZNLM=": {
            "valueMac": {
              "type": "Buffer",
              "data": "b4AnPsdBCrIHic5BMvGFCoEy5j/FWbDUDkScSDfAJqk="
            }
          },
          "8F7dR4iWks8xRIBQr8vrQ/EJyUVQaLLN6b4REbx+HWU=": {
            "valueMac": {
              "type": "Buffer",
              "data": "wODEqFsdr2md01O2ZVU9vXHZ/U5zqzhw9B+0e2zVjcI="
            }
          },
          "5S/gPSgpyhpdTky441nmWQyD+cUAJ2vnUW3EvIRThlk=": {
            "valueMac": {
              "type": "Buffer",
              "data": "YUuQQHGd4pipXToiAfWVtEeeWy7lzHjdT5f/znagYzg="
            }
          },
          "lHHZKmDdQpNqNMcp5Iy0PUvU7+2gyZwIOXtk1w+PJBU=": {
            "valueMac": {
              "type": "Buffer",
              "data": "vQF5eiU3H+gJuzFHPmc8GgWKsDEy1el6+gDXYIubXnI="
            }
          },
          "rGoq/TId+tGQKaDCH+uIOnurbKbiknUWeizqEME9Vm8=": {
            "valueMac": {
              "type": "Buffer",
              "data": "jGCAEa/WHOX2K7pGaJvf15aZTUaZM6dlJ1ETOJZbOzo="
            }
          },
          "MJTh+Tn/gsRR0bB06gh5wrCUGYg0KPku0WafclFhEgk=": {
            "valueMac": {
              "type": "Buffer",
              "data": "+uX+OoIqeQiulwlLxoJY3szf43RC96W6n9YgZDbNzgM="
            }
          },
          "+l/7CHIkjhlswmxOzFAUU7ArXHKIAPC13xWhkwXcXd0=": {
            "valueMac": {
              "type": "Buffer",
              "data": "ruaSKE3LIpo/SVnkUc07gBrU3Njj5LAHKQmHW6V1Fno="
            }
          },
          "gBi3hafgARdZLwHrULjEW7nfruDOpJ+lIVyjRxhXQRE=": {
            "valueMac": {
              "type": "Buffer",
              "data": "OdSbF0wFy3/0Io+NtVStH59qDtpQup5mZ/TGUw0r2LQ="
            }
          },
          "kLt/tl4xjZw5gSNdwkG+fbSS+L1KeCWM+IU2fXt5MpE=": {
            "valueMac": {
              "type": "Buffer",
              "data": "Ep6zK5N5+KHrFmiVo1J46PJzixJzWRNozrUHEFTJDsQ="
            }
          },
          "gqfmKwLeub/qfalC3FLLr/tKypM/DEJeGZ1aS1ob6iM=": {
            "valueMac": {
              "type": "Buffer",
              "data": "7dNX34x6bDTUU51FW7FInrIAINXFZ+9laS8qTYnJRXY="
            }
          },
          "z9lnDoZ1mF9TS+PeW3Zfp6o977sxF/xCmi1s5WHaogM=": {
            "valueMac": {
              "type": "Buffer",
              "data": "jEuCfkfscHCibDuTBVxSTEmqoN8s2+0sBFKZbZTS7/A="
            }
          },
          "C2NyP04ejaFW1qaDkwYv8MwT9Fm7eWYRHmd5BySDeK8=": {
            "valueMac": {
              "type": "Buffer",
              "data": "uYph62W/xXNt+2PRfVsVQ9Q4b6KtMTzGFgjOGcL4ilw="
            }
          },
          "AV/eH2noDl8vMvPWtVRaphMX36KI15D5bTnDzvXEDvo=": {
            "valueMac": {
              "type": "Buffer",
              "data": "p2KJtOLON4GNwyPMQ7xRDLS/ABrbWVENQlGioDf+0kc="
            }
          },
          "4QrKVjtKdTDNc5zGWNoxowd68/YuGYNhmQdYE6/7ids=": {
            "valueMac": {
              "type": "Buffer",
              "data": "wuwKtZqxMxIBcFrEiHf2iRaYZAGXD80EUJmt+BWPbPg="
            }
          },
          "HhsOc8af5gADwRIrtzIw970XLl1hpV0WYTM1LZbIJTw=": {
            "valueMac": {
              "type": "Buffer",
              "data": "vyuvC3me4pbU1mfyFuFoFdLAySpz/OnNAwZOafG84xw="
            }
          },
          "/sd4m9ItJTgC00l6V3H3GQoxg1d2nj2IdKbq3aQtuow=": {
            "valueMac": {
              "type": "Buffer",
              "data": "c65viGinnh1lsVTMBSgfsXGpaUQSDwcJSWnCfZWPBXU="
            }
          },
          "70aK59RCbaVl1TTT/CMZJIHWUjN+p64vnTpxJFQiLYg=": {
            "valueMac": {
              "type": "Buffer",
              "data": "0e7LICw/xZ4p7Lza9fDNsv/6KVZH/PHxZy6OKi1LJF4="
            }
          },
          "Begffa3HpYRy2eqh9xzu9+WEe2HqUkB9XaGixyEUSj4=": {
            "valueMac": {
              "type": "Buffer",
              "data": "OcbaNeozsHhQa1fS2oFJPrEJmqtDLULmcCxLxQ38RJg="
            }
          },
          "Nq0YAj8r4lpcyrj/V22C/QG5qP01HSGsbz1VZVe5HVs=": {
            "valueMac": {
              "type": "Buffer",
              "data": "Gjzqb7twh3kUSbDasX9vrxtLpVZJoMSZccBa6eT/XFg="
            }
          },
          "FI/fIHEUPx/cfkvo6ftWFD8hzbsDowHf1X8vM0sNdTs=": {
            "valueMac": {
              "type": "Buffer",
              "data": "3I/4G+kf8LwLgjRc9Rg+5frzWT3yqmpUY5IekrNlEn4="
            }
          },
          "hSJZ9kA9aa6ty17e73BI/63zrgaUC+TWLzPEPPgObLA=": {
            "valueMac": {
              "type": "Buffer",
              "data": "TY0aQ7b/OknrSAJm4IaGIfOu/ss8RDs6b1C/ahLPkLc="
            }
          },
          "Lddi4yi+AvMio+vwW7vlJMIcV2O+jw48Tg1UlsP7/X0=": {
            "valueMac": {
              "type": "Buffer",
              "data": "NAYMYUTTcgFkROOudYcBuCfyDD1cXgGXljHDiv+K43I="
            }
          },
          "1JiIdkTIF6rCgLtdbV3V/xS0IXgnbOSGc9dYzHNfauM=": {
            "valueMac": {
              "type": "Buffer",
              "data": "SP4KYN0dNa99Vob5pjDy+emtelBLzKJtVc7cxrH2RD8="
            }
          },
          "mhWerLnCbY/M4os/GZRkAzQ5y/+kkro2vCLaxRH+n1E=": {
            "valueMac": {
              "type": "Buffer",
              "data": "/M6PoKEMWLBIzsHgsMajW+bjOtn7K8k534hNjp0ZrBk="
            }
          },
          "UBGtHR41P4SLHQ8ZIqZCNmWyQfEU2QmlVRypS42EuDc=": {
            "valueMac": {
              "type": "Buffer",
              "data": "jLo9T+OJccHzwrlWQoXo55N6ubVIDcFX0po3OkTO2h8="
            }
          },
          "c+141CeyqJeXGLQ6P5qJfyql3LeECL6pKxs7c73m+A4=": {
            "valueMac": {
              "type": "Buffer",
              "data": "g5ZHmf5uJBTrMpxdSd8rxAsbi5+if113V/h8+n5x+d0="
            }
          },
          "EYT1n901Yz/LdGuvWBHM+gnvwj92NwzL/PtennGM5H8=": {
            "valueMac": {
              "type": "Buffer",
              "data": "qXLGz8lI4FD4yivL2o1y9LNv6u2O+JKrYMDwiqP5gzY="
            }
          },
          "QFZWtykhMkqrVmLQSXKzM4YSBn76xT5p9pfGYrtqi9E=": {
            "valueMac": {
              "type": "Buffer",
              "data": "oUkNa7m8Rxc+q1/NGPQZK/SeMj8C2rZOFhLGFdyFg0w="
            }
          },
          "Jf6rlsF5CsyKPWUwRoryDPuLa4wYLvqGDJ1AcK3izT4=": {
            "valueMac": {
              "type": "Buffer",
              "data": "0TAf2aRU6k6whe+TTeYSDXx5oI8lYT2vsfAf4+IIy/Q="
            }
          },
          "vijm2wc9eQ/8Ej1fFMOEL1CB0CBtxkKljR5jmld6lHU=": {
            "valueMac": {
              "type": "Buffer",
              "data": "Zq7WTk6ozC/MhtYdc4Rves6PPxytpOW8JCejyoEKhck="
            }
          },
          "WRB4CPUKJehLrY/t7En8m38U1kfgP+vFE5i+yp3ehFA=": {
            "valueMac": {
              "type": "Buffer",
              "data": "55B+IkXF8lHQwe76r5ye6DLjfdmNLC9zAFyRPn217Io="
            }
          },
          "ts1QSmS2qwPwZXnYqfQCTWn/e9z2SjgX9Nc9168nk1I=": {
            "valueMac": {
              "type": "Buffer",
              "data": "4mWV0Uidnf5fn/uZ8xfkI5F/A0t+Xd8oB9TudE9ovkQ="
            }
          },
          "Vi4evCGfBOXfglkGIzGIIXdnuZN+251+PLB7nwZEie4=": {
            "valueMac": {
              "type": "Buffer",
              "data": "ERtGoXgy1yXmvAAx95LFwPIWNsnKuHIPcYQ45nu33BM="
            }
          },
          "lfc8/sD0oygSI3EEe86yb12nwunmtFJ5vRJD7IS3sl4=": {
            "valueMac": {
              "type": "Buffer",
              "data": "lpmxKkqu6tuVZfgRr2p10T1Hnju8WuIuC4+peKtbYg4="
            }
          },
          "kFhp+3yR7p6ocFQ+iWEhh9ZPgyagb07S6JmL2y300Bs=": {
            "valueMac": {
              "type": "Buffer",
              "data": "EPrFcR2YS2TRBQsDgR3LtMKye4U/WZ2nBP76FN87kFc="
            }
          },
          "yt3Zf5PX9TZ9pnPra28tUfPcz6+Znt0t6GlP8ELTFyE=": {
            "valueMac": {
              "type": "Buffer",
              "data": "kWziJGtHeA/bhk0794FYoLjhlmIh/5NIjgqnzBK8uBc="
            }
          },
          "/iuj++TQvbNYuYeDN0IOEW6tZeqzRPXMW6PSEE83SXk=": {
            "valueMac": {
              "type": "Buffer",
              "data": "ICVxgHDRqN836as+1etNY8PTp4OhW22OtJJQwbMQtUo="
            }
          },
          "4WufOnW4vA/9LyFMBMWJOP/exe3gIQrAmpmJR90g/Ts=": {
            "valueMac": {
              "type": "Buffer",
              "data": "EmbehSRGrKrBuGs5vE5gLDzFhPUnqpRse+MPURLdeP0="
            }
          },
          "UdwcBjyH+TyifUhXgTMBrczIplNveNkI7APw724hptc=": {
            "valueMac": {
              "type": "Buffer",
              "data": "Q/5rc5LvW3Nz2PjGUlxWM5x5fTTf3wgEgJ2B0rDgURY="
            }
          },
          "ivYaG7imte+Guf+EChkEIiGDs19j75qJ4PR8vCkP9yQ=": {
            "valueMac": {
              "type": "Buffer",
              "data": "TLzDDTjpOtC0xKRumRLBc3GIstvy7dCKm4sBw1JK73g="
            }
          },
          "7y4eaBVo3SJz13lJ35h3d4rTIhbUaOyDa0uaJujBtQg=": {
            "valueMac": {
              "type": "Buffer",
              "data": "aVPqSNDBCVwkptl2+vmCilJjdxF2p66099Tp06dZ3iY="
            }
          },
          "bSuSzFYrgQgHOPyPdmvN6rVfptbcEE9N4Srf2T57FcE=": {
            "valueMac": {
              "type": "Buffer",
              "data": "Vtg/pba132gCds5E8v5or6Lm9M2/fWnTfJLE776JzTM="
            }
          },
          "WkPu+HEMlQ3dAfK7sRNYzqz/5B4jCnpAZVvdn78ROQw=": {
            "valueMac": {
              "type": "Buffer",
              "data": "K0wOJPI5340V91QUWjvaoHhuO6gopUJUayiXuMWbg/g="
            }
          },
          "KAVUjPdT6bnOrLRvGxJSRVnJj0IjlUjBu4IVnY2c9uM=": {
            "valueMac": {
              "type": "Buffer",
              "data": "IWD5QMBGhvXXLd4hrXmO7wgp1XTkxIa/4jrfFP486uQ="
            }
          },
          "90QYEYf33GNQKvQtd4QBUC9FeRpG03G8iDj9YzobmT4=": {
            "valueMac": {
              "type": "Buffer",
              "data": "p+dDrfiaCBrvVkhuF7OA4JKkifQWKlqX+ZJXk33qVtY="
            }
          },
          "ofpu4qjoz2CZrR8KD/O+yIESVwMXPFzIeb9+9Dk1DWg=": {
            "valueMac": {
              "type": "Buffer",
              "data": "l6+b5J8D34vB5FBwLVDAe9UpiGvKJ3ukRPENle7eZiw="
            }
          },
          "lf2+tcAVC/oas4qL88JSW1xmDUtHiM4Oa+dw1U3TQ2Y=": {
            "valueMac": {
              "type": "Buffer",
              "data": "S8FD05Nz5s8+HpX9uMlexmN9QJJHzM/JL28ICf7MAoQ="
            }
          },
          "0ZKsXU1bJYTc3nm6Sn0jexetJw0737dVD8R7bdQb6TU=": {
            "valueMac": {
              "type": "Buffer",
              "data": "V24l7DagD9PYpDC68gqSn3pL+Qc6TGT+iJd430L3Xbk="
            }
          },
          "lmVouGMrNGcBiY5WBHUkiveAQZwmPFrToZ8LNeORqHo=": {
            "valueMac": {
              "type": "Buffer",
              "data": "t2x+vqWlWmtdYtqxMFvSBs+G1a8qwYXCoJvIGdtyBsc="
            }
          },
          "5uaIb9GRTbWHz8C7fj+g5rtsGdsiw+IfrKbAH6+zoSo=": {
            "valueMac": {
              "type": "Buffer",
              "data": "QIjqqH7jWlXaE8xI+X+DP06UGGll+g7JHjV5h1XqWMQ="
            }
          },
          "cUR1AwSZcODihESjZUdm9TVuPrEz6kr0y9wUbktodHs=": {
            "valueMac": {
              "type": "Buffer",
              "data": "jzYhlFhn2m2AM+9GcJ6SuS4vkrIoMa3qyLtlpi6pstc="
            }
          },
          "Dz8im7CLzgQBnZOzWjOUVisAqNrZrFna80BRIIrnnHE=": {
            "valueMac": {
              "type": "Buffer",
              "data": "K5GEXcq7ZBBiHnLCrB9uhjArqjOzldyhSkAjWBa4vNw="
            }
          },
          "I9QmEqaeLB+Zl4yXOnHRb3XwX92My8pc0L7y0DAEC+o=": {
            "valueMac": {
              "type": "Buffer",
              "data": "GWDOfpJme10/o9HnwS3KTcE69qOkf405Y0LGh/d762s="
            }
          },
          "0ZPLdvk7Q1QuRU8Tw1f98jC+SQmNSsKGzBAbconWZ4g=": {
            "valueMac": {
              "type": "Buffer",
              "data": "mWv1Vaghdx5YBtBlC2vNSVXMvXwI+FJiOOHDExhgCOU="
            }
          },
          "aJQbCBVES7Kv4MqJArWXzmwcutHhUQckKK1c8uLXdTw=": {
            "valueMac": {
              "type": "Buffer",
              "data": "1l51nqBdMIAqkpM4aKfsktST4EeZvNDXXH7hxgP56j0="
            }
          },
          "R1KVu/JveNqMgQIYklT8KMgvC90fCBvFqwkYH9F/iQo=": {
            "valueMac": {
              "type": "Buffer",
              "data": "py/igTFB6LfLhXs0iJ93BAUPXeL19ffMDHvI1qvlQG0="
            }
          },
          "WV3cJjfalTLiGp5i5pa4GXV4195SaL2VjH2FkGitOgQ=": {
            "valueMac": {
              "type": "Buffer",
              "data": "2OV70maV6X377CH3g7ZCzg3m+adeMp7u4QElBNucuVQ="
            }
          },
          "ZPR+42nsaakSe5NgWGJGienb5FzS4sgTgPg6Aow116I=": {
            "valueMac": {
              "type": "Buffer",
              "data": "YlPKYBLo+l32v4TN9yt0/MO8zROcPrgAG+lb7XmRXwg="
            }
          },
          "rQ98IGvX75EuZbuQMdBSAJaGYVB07uoGqmIrw3ge0cA=": {
            "valueMac": {
              "type": "Buffer",
              "data": "vbzV8Vp+EQr2CX+JZED/ruel8xUJLJZpoz4Lc9xQx/4="
            }
          },
          "QzGUsCGmZ7stutGTCvyaksha/XITiikcoLq+Al8sMMk=": {
            "valueMac": {
              "type": "Buffer",
              "data": "esviAAQ1OAiIbBQjLZTB8VeagRVzRO5dqGhKpuGfEzc="
            }
          },
          "5xaZIbn9TiPw3GlT5issls+U9LYGX+LBS+nydhl9EmE=": {
            "valueMac": {
              "type": "Buffer",
              "data": "gtXYnUrOzpn0fMbVpbk6nGsyEWL2mA4z6XjfZoOv0nA="
            }
          },
          "xQgnEzde9GTPO7K5sDnFdQ+bGk3m8Z7FIbtYQ1mjlKA=": {
            "valueMac": {
              "type": "Buffer",
              "data": "8PGnhzbHAxPgBho6DLRx4cVneaXBKi7IQcqmdMXwXG4="
            }
          },
          "vDTh1yTxe5mOvCdoDWIrI2FhYoq5wkNxE85yisbvCds=": {
            "valueMac": {
              "type": "Buffer",
              "data": "X9m+8dHesWirky2VRJE+R7sd14VCcYMpzMWUKsZkFTs="
            }
          },
          "FdXA0c8BUzJnCddmN6qBzptCwAMWtny7hyih5eYPnnE=": {
            "valueMac": {
              "type": "Buffer",
              "data": "gAKI0koY7SNbqqgPV/erDpOVySPLHG5GXyKqKGI6VU0="
            }
          },
          "Ks25znWwjwt4HNV7dIjhwXtGAXN1yeBbd0MxaCd9KNI=": {
            "valueMac": {
              "type": "Buffer",
              "data": "bpl0Snq7dbc7YleEHSCjr3cMoOYb3ve3I2/q1DlRzVk="
            }
          },
          "nO93EPXtmL+fsqPRTol336+ljurXpIZKIcRsjd3bUZk=": {
            "valueMac": {
              "type": "Buffer",
              "data": "PWEsKvaMHmLWlB2wIDCvVecf2rsaPBOlwojTy2FbWOI="
            }
          },
          "vhLB0Erek2ai9WmtyyY0R8Qk21/6v60ipLQnYkOdMFA=": {
            "valueMac": {
              "type": "Buffer",
              "data": "gX0UK1f+RzLDh7HAJHYKV5KUA7QWyVUQhpUydfNiYyg="
            }
          },
          "jB0QgQppHajyFgdTPuTroytJmXyF5XnVsAw/aVH6MrY=": {
            "valueMac": {
              "type": "Buffer",
              "data": "Vxg2NamAFJv90kISA8zxMhesNmwIhdkohLvLSYGjjKw="
            }
          },
          "28oHg8200PGcfGyTR0GHyfk4Oh6pWnKwHT7iDGPPqOk=": {
            "valueMac": {
              "type": "Buffer",
              "data": "srttWUeMdyN3YGxAvD5ul6rflF6cvHwF1NWOoujRxNs="
            }
          },
          "6d+avAf6W8+DcYwbLwK7abAGmi+apWGvokj0wJmuP+I=": {
            "valueMac": {
              "type": "Buffer",
              "data": "XlssTEiRgx/Yz3pO4O6OrECeg0J3r/hd+2opsEeQJ7w="
            }
          },
          "HGT0o4fGhnJo3tcbT+47w2Rg2cRV+ClAuCshPOzfe5U=": {
            "valueMac": {
              "type": "Buffer",
              "data": "Jn0qp0rF9YFvKZ6QrFPkM7YuqyuDi5hns0qG9T7k5eA="
            }
          },
          "KZdwEPwfJQiorT64lKDUly1KrblxMimoMIXVqWEor7Y=": {
            "valueMac": {
              "type": "Buffer",
              "data": "9I53uR3FDc7HN1Ls3aCvtUDYqzUrc88EMa2utkWfD5A="
            }
          },
          "cO3Wfzpun2O3jc2xvS7ZiCIbFk9v2OmMeREbAoSG3ms=": {
            "valueMac": {
              "type": "Buffer",
              "data": "8vBDUwTy5iUFjkG14fZnNW1/rNUj9Bujiif+yjMSBvs="
            }
          },
          "4cMDzxvg7ZC+1kZYX9Iqp95GWFtXxqATlQ8a5UaM8CA=": {
            "valueMac": {
              "type": "Buffer",
              "data": "4ieP7JITFayiiN+lNasglfo82vgXny66b4jSAYFprTk="
            }
          },
          "o6y72vi94MpJ1wKbDioQbZklKwZ4qxUd0Qq8JhRY5E8=": {
            "valueMac": {
              "type": "Buffer",
              "data": "IDLZPyzB+PsgmjGQ88FIeAxZstus3/6vat9xi2rfgrw="
            }
          },
          "U2lBWEqO5AWjMp1clT2R0Leu9IRQkTMr8ney4Rzbf5M=": {
            "valueMac": {
              "type": "Buffer",
              "data": "MkLfsVEOEIRm/DYSQVwQD4/Q/LkQv8xn2/s7WX0vGkY="
            }
          },
          "tGb35SBNi5OnsxSqbzhCfmNqcAi5rVpE5EuV9cDvf2w=": {
            "valueMac": {
              "type": "Buffer",
              "data": "Rim/k3qCAIOnNGQkyN6DsuA/HtnwSsxdqZcLxVRATgU="
            }
          },
          "xVS9f+/mDo44a+2y7KkYHSQ8TZYSGtBYNLcmWniTwJA=": {
            "valueMac": {
              "type": "Buffer",
              "data": "ELnZLcBHWRfzu+fawRdiLoMjqaCjpa4ud4MXjRZRCW4="
            }
          },
          "U1QpDNAVT2Z4KEmoKhu1PGdPZrgT2bbicCkNO7Xv2IU=": {
            "valueMac": {
              "type": "Buffer",
              "data": "FnFKZdCi5KLy+Lg0j/KJIvA6AFvydpNjhBD05T7770A="
            }
          },
          "Yo63f2u/NsQyvuvmymphvgLUTh7bx/bIyCXO0DhOwFU=": {
            "valueMac": {
              "type": "Buffer",
              "data": "dnhqe45SYl/BSj4+p8DgiGfiskV1G4BY/IwPD2omFFw="
            }
          }
        }
      },
      "regular_high": {
        "version": 1,
        "hash": {
          "type": "Buffer",
          "data": "knkytiTRo6FyydV3gvs6mauim7xnmHqx83D2KGJvXD/KoPNkTZSLeEegUVrnZ1tzCppY73kXdj6O9q4ZlE9jISO3cP/97I3ZutGbjNvs84He5IMgCVRbdZmLWR9rUoghKxRZ9oOOydcxkiWzgGF55T+b+zJf3mXeIaSIpXQKoUA="
        },
        "indexValueMap": {
          "bHNuLP796LcZnDQpK+faZlvz9MB2Nvhe96ud5BVjRhw=": {
            "valueMac": {
              "type": "Buffer",
              "data": "k3N/zNfR6T/ofUeOsHlSQMHb+atJSKm7ahf85w6qGQM="
            }
          },
          "GV+HeWGKr97Hd/TZ38we0vLMSstVIY+5ajqkFnfkUFc=": {
            "valueMac": {
              "type": "Buffer",
              "data": "34Ha8IzUmGE9W/8QhD0KMI9bvs1v6es26oZwUmQ+uZ0="
            }
          },
          "+vhNh/MddJPbY3kc2G8gevMRUxU8TkGMKgCk7BQeO7Y=": {
            "valueMac": {
              "type": "Buffer",
              "data": "JLnMvVmidLVEv20jiC+prTeTt42JGn0SjekP1Eqyt9w="
            }
          },
          "z5kBtFSwwb193seL/DSwHlkyjEulJhBypaLBUVksQio=": {
            "valueMac": {
              "type": "Buffer",
              "data": "bUrDgPapOwrW+RlPiZcih3n7K4umVc0zuYqDmeLrjNQ="
            }
          }
        }
      },
      "regular_low": {
        "version": 1,
        "hash": {
          "type": "Buffer",
          "data": "HX8x8PYJZXfwFPZv3TlsPK/irxO2U78sdfKh+Q2+RIcL9/Dh3sGyx7qAXHReO6jYQ3siYs5AKDBgem1kq/jCIWhtJ087pY9t/0qJsdq3w8v+0I1edPMpalGNEMSpLnwQES4454bN1qikL5xTqWmuP3+narDn2ouz/CHS25BYxvA="
        },
        "indexValueMap": {
          "l5BdBXEQUgyYhVSW8W/cEI4y2stNxZMlolaJK0h8zJI=": {
            "valueMac": {
              "type": "Buffer",
              "data": "rTrAQkWTgWHO62pCaulKCP3xAeg4m36FtYOPpV+HpLM="
            }
          },
          "kRnmhuatVLj8boJio743ycrcePucwtpgPsRteuWpjRA=": {
            "valueMac": {
              "type": "Buffer",
              "data": "HYG9lw2rwFSEOKo6/wJWP890o6GBkkoSBhmyi4agkgM="
            }
          },
          "yahWbM1fy5FTJ4lTSbFxSEeMH84AONIYB+Q8QOY8moU=": {
            "valueMac": {
              "type": "Buffer",
              "data": "6mlSyKIDX52289v4iEZRbGNORznKMXzF/yZZ729y8gw="
            }
          },
          "STItr7IuXmnnn0gba4merTGg+1d9StrsiuYiqTu28EY=": {
            "valueMac": {
              "type": "Buffer",
              "data": "lgJCTTvYQuxUSCV4BDXxefEXHFpTrew1RccbgmU/fSQ="
            }
          },
          "ipzaTudr5erwrJbYD+OQ8fWQGKsgEXY4jQazM3BTYMg=": {
            "valueMac": {
              "type": "Buffer",
              "data": "XjxylWX8nWWMrzYhG7SzwdMt+FmVGhxF5tLRoR/6JqA="
            }
          },
          "RnKofAuU+g/kqiWPIAEf5XZscBRYx/IrVZCn0rvQCNo=": {
            "valueMac": {
              "type": "Buffer",
              "data": "e0VUqf0rMuEDJcRhn8mlLGwScVYIfQkRsiMmmbWdwf0="
            }
          },
          "gi/0xs9qalauLepMbuOlal8cWY1XL50yDEg0rdDLdl8=": {
            "valueMac": {
              "type": "Buffer",
              "data": "yjDEMvvgAs2atxy0GGgsVHrAZK2rAMY4dHVk9YOdlLw="
            }
          }
        }
      }
    },
    "senderKeys": {
      "120363043216331789@g.us::6283849345181::0": [
        {
          "senderKeyId": 1869151311,
          "senderChainKey": {
            "iteration": 2,
            "seed": "IWbcf5UM7nqQ4MCkl7HCiMUdju7jgNd81WtkCRLmMS8="
          },
          "senderSigningKey": {
            "public": "BdzDK8hy7FRku00P2yvWlp7P1FoVHJrCfMGlVdykgCEU"
          }
        }
      ],
      "120363043216331789@g.us::6283121411380::0": [
        {
          "senderKeyId": 72014258,
          "senderChainKey": {
            "iteration": 4,
            "seed": "us8yvm7MemtO/pKrH6bgN3Z1gpwZhO2gZowVXueFHIo="
          },
          "senderSigningKey": {
            "public": "Ba2svTo6gUHG/7XtynetMpNWo3WC1kCpQ/Xns3cGipR7"
          }
        }
      ],
      "120363043216331789@g.us::6281213006650::0": [
        {
          "senderKeyId": 389238881,
          "senderChainKey": {
            "iteration": 1,
            "seed": "CHG2kaTXPl04ngzUgsiX5QyYQMJfuAmodPJvjHkroRs="
          },
          "senderSigningKey": {
            "public": "BbVyDqIjva0bCV/ZiCHiJzh92hmhe8hWXtQLuHdN0EBW"
          }
        }
      ],
      "6282123159415-1588747881@g.us::6285870620735::0": [
        {
          "senderKeyId": 2049380458,
          "senderChainKey": {
            "iteration": 42,
            "seed": "3lOTlSsSdo+s8uuQK1d8d4+kCioMSVkaEMswnyeH5gQ="
          },
          "senderSigningKey": {
            "public": "BdyhxuW9+H+PsPRNknO7UWK9oxuNWXoiZ/76aIL8kzIG"
          }
        }
      ]
    }
  }
}